lorenzpy/__init__.py
lorenzpy/measures.py
lorenzpy/plot/__init__.py
lorenzpy/plot/plot.py
lorenzpy/simulations/__init__.py
lorenzpy/simulations/autonomous_flows.py
lorenzpy/simulations/base.py
lorenzpy/simulations/discrete_maps.py
lorenzpy/simulations/driven_systems.py
lorenzpy/simulations/others.py
lorenzpy/simulations/solvers.py
lorenzpy-0.0.2.dist-info/LICENSE
lorenzpy-0.0.2.dist-info/METADATA
lorenzpy-0.0.2.dist-info/WHEEL
lorenzpy-0.0.2.dist-info/top_level.txt
lorenzpy-0.0.2.dist-info/RECORD
