Metadata-Version: 2.1
Name: lorenzpy
Version: 0.0.2
Summary: A Python package to simulate and measure chaotic dynamical systems.
Author-email: Dennis Duncan <DuncDennis@gmail.com>
Maintainer-email: Dennis Duncan <DuncDennis@gmail.com>
License: MIT License
Project-URL: homepage, https://github.com/DuncDennis/lorenzpy
Project-URL: repository, https://github.com/DuncDennis/lorenzpy
Project-URL: documentation, https://duncdennis.github.io/lorenzpy/
Project-URL: changelog, https://github.com/DuncDennis/lorenzpy/blob/main/CHANGELOG.md
Classifier: Programming Language :: Python :: 3
Classifier: License :: OSI Approved :: MIT License
Classifier: Operating System :: OS Independent
Requires-Python: >=3.8
License-File: LICENSE
Requires-Dist: numpy >=1.22.0
Requires-Dist: scipy >=1.10.0
Provides-Extra: dev
Requires-Dist: pytest ==7.2.0 ; extra == 'dev'
Requires-Dist: pytest-cov ==4.0 ; extra == 'dev'
Requires-Dist: black ==23.1.0 ; extra == 'dev'
Requires-Dist: mypy ==1.1.1 ; extra == 'dev'
Requires-Dist: ruff ==0.1.0 ; extra == 'dev'
Requires-Dist: mkdocs ; extra == 'dev'
Requires-Dist: mkdocstrings[python] ; extra == 'dev'
Requires-Dist: mkdocs-material ; extra == 'dev'
Requires-Dist: pre-commit ==3.1.1 ; extra == 'dev'
Provides-Extra: plot
Requires-Dist: matplotlib >=3.5 ; extra == 'plot'
